{"sections":{"main":{"type":"page","disabled":true,"settings":{}},"slider_PHgJdg":{"type":"slider","blocks":{"video_slide_fMTFWa":{"type":"video_slide","settings":{"video":"https:\/\/cdn.shopify.com\/videos\/c\/o\/v\/2dc7a1d3d2384122997c47be23af4925.mp4","content_in_container":false,"content_position":"center middle","text_alignment":"center","text_size":"medium","text_color":"black","subheading":"","title":"","description":"","vdo_head_font_size":24,"image_link":"","button_text":"","button_link":"","button_text2":"","button_link2":"","button_style":"sf__btn-primary","button_size":"","show_footer":false,"footer_alignment":"end","footer_text":"New Collection","footer_button":"Shop Now","footer_link":""}}},"block_order":["video_slide_fMTFWa"],"settings":{"desktop-show":false,"slider_heading":"Home Deco","slider_para":"Festive ways to create seasonal cheer with the ones you love","slider_button":"SHOP NOW","button_link":"shopify:\/\/collections\/all","font_size":70,"para_font_size":24,"container":"container-fluid","slideshow_height":"large","show_overlay":false,"dots_position":"bottom","dots_color":"dark","back_contain":false,"show_dots":true,"show_arrows":true,"autorotate":true,"autorotate_speed":5,"backgroundcolor":"#041e3a","back-image":"shopify:\/\/shop_images\/Home-deco-Clod9linens.heic","custom_class":"cus_top_overlap s_heading"}}},"order":["main","slider_PHgJdg"]}